Metadata-Version: 2.1
Name: learning-path-package
Version: 0.0
Summary: functions to draw beautiful plots from dataframes, and functions to calculate ROC curves
Author-email: hernangarciamayoral@gmail.com
License: UNKNOWN
Platform: UNKNOWN
